meticulous/__init__.py
meticulous/__main__.py
meticulous/_github.py
meticulous/_process.py
meticulous/_secrets.py
meticulous/_sources.py
meticulous/_storage.py
meticulous/version.py
meticulous-0.9.1.dist-info/METADATA
meticulous-0.9.1.dist-info/WHEEL
meticulous-0.9.1.dist-info/top_level.txt
meticulous-0.9.1.dist-info/RECORD
