Metadata-Version: 2.1
Name: meticulous
Version: 0.9.1
Summary: Automate process of forking and running pyspelling on a repository to locate typos.
Home-page: https://github.com/timgates42/meticulous
Author: Tim Gates
Author-email: tim.gates@iress.com
Maintainer: Tim Gates
Maintainer-email: tim.gates@iress.com
License: GPLv3+
Platform: UNKNOWN
Classifier: Development Status :: 4 - Beta
Classifier: Programming Language :: Python
Classifier: Programming Language :: Python :: 3
Classifier: Programming Language :: Python :: 3.6
Classifier: Programming Language :: Python :: 3.7
Classifier: Programming Language :: Python :: 3.8
Classifier: Programming Language :: Python :: Implementation :: CPython
Classifier: Programming Language :: Python :: Implementation :: PyPy
Classifier: Operating System :: OS Independent
Classifier: License :: OSI Approved :: GNU General Public License v3 (GPLv3)
Requires-Python: >=3.6
Requires-Dist: PyGithub
Requires-Dist: plumbum
Requires-Dist: spelling
Requires-Dist: PyInquirer
Requires-Dist: requests
